api_session/__init__.py
api_session/py.typed
api_session-1.5.3.dist-info/METADATA
api_session-1.5.3.dist-info/WHEEL
api_session-1.5.3.dist-info/licenses/LICENSE
api_session-1.5.3.dist-info/RECORD
