Metadata-Version: 2.4
Name: api-session
Version: 1.5.3
Summary: requests.Session to work with JSON APIs
Project-URL: Homepage, https://github.com/Bixoto/api-session
Author-email: Baptiste Fontaine <baptiste@bixoto.com>
License-Expression: MIT
License-File: LICENSE
Classifier: Development Status :: 5 - Production/Stable
Classifier: License :: OSI Approved :: MIT License
Classifier: Programming Language :: Python :: 3
Requires-Python: >=3.9
Requires-Dist: requests<3,>=2.26
